[{"id":"01","title":"entangled life fungi","timestamp":"2/20/2040","height":32,"notes":{"0":"60% of enzymes used in industry generated by fungi. 15% of all vaccines come from engineered yeast. Even Citric acid (used in fizzy drinks) come from fungi","1":"Central to these mutualistic relationships are mycorrhizae, which are associations between fungal mycelium and plant roots. Mycorrhizal fungi colonize the root systems of plants, extending far into the soil."},"url":"https://www.bookey.app/book/entangled-life","image":"entangled-life.jpg"},{"id":"02","title":"next total solar eclipse","timestamp":"08/12/2045","height":64,"notes":{"0":"Montana, North Dakota and South Dakota.","1":""},"url":"https://www.bookey.app/book/entangled-life","image":"c62252dc91a7ba94ab3ffd535681ee173f8fe2bf-932x618.png"},{"id":"03","title":"thailand floating theater, Bulo Ole Scheeren","timestamp":"08/12/2045","height":64,"notes":{"0":"Local fishermen farm lobsters on rafts. Wooden frames are tied by rubber straps to foam blocks wrapped in mosquito nets. A simple construction. A local technique.","1":"disassembled and goes back to local community"},"url":"https://buro-os.com/projects/archipelago-cinema-thailand","image":"Floating-Movie-Theater-16-980x701.jpg"},{"id":"04","title":"sustainable farming at home, pippa greenwood","timestamp":"08/12/2045","height":40,"notes":{"0":"","1":""},"url":"https://www.frombritainwithlove.com/sustainable-garden-ideas-from-pippa-greenwood/","image":"pippa-greenwood-organic-sustainable-gardening.jpg"},{"id":"05","title":"el ojo, argentina","timestamp":"08/12/2045","height":32,"notes":{"0":"As the island is constantly rotating on its own axis due to the flow of the river beneath it, shearing occurs around its outer edge, eroding the island into its circular shape, similar to ice disks.","1":""},"url":"","image":"el-ojo-argentina.jpg"},{"id":"9edbb09d-9fbd-4d01-be6a-33ae49197b68","title":"testy test","description":"cool stuff","height":40,"file":""},{"id":"e05561b3-f05e-41f9-af14-53126478c3b6","title":"testing 2","description":"cool stuff 2","height":64,"file":"C:\\fakepath\\2D Canvas.png"},{"id":"239bb11f-8c97-4a1b-8cd0-6a487dd43e8f","title":"testing again","description":"all the time","file":""},{"id":"9defd0f7-8fd9-496d-a9fd-5cf58a02726c","title":"testing again","description":"all the time","file":""},{"id":"7e40f533-c27c-42e0-a617-f762fe5f0bbb","title":"testing again","description":"all the time","file":""},{"id":"5eeab9aa-cc60-494b-9ab0-f6f5c654833b","title":"asdasd","description":"dasds","file":""},{"id":"886281da-f366-4f96-a8e8-81dc0d0a6f89","title":"asdasd","description":"asdasd","file":""},{"id":"148229f9-bc32-4c27-a23f-ff665bddaa8c","title":"asdasd","description":"asdasd","file":""},{"id":"da7825cd-e9ae-4745-b61c-30c11dbad400","title":"zesty testy","description":"hehe","file":""},{"id":"6396cdd9-7e48-4974-97da-fd4a85b6e694","title":"zesty testy2","description":"hehe2","file":""},{"id":"fc5d4b28-bdc8-47be-8f11-b6e445985da3","title":"er","description":"errr","file":""},{"id":"c501ba2b-f91e-4b85-8d9d-3b2a952b839e","title":"er","description":"errr","file":""},{"id":"97a42f00-ae4f-4029-9f4c-88bab93e7cc4","title":"eee","description":"reee","file":""},{"id":"9329e33e-de83-40bb-9583-77da85829f94","title":"sd","description":"er","file":""},{"id":"5e4fab6f-2947-4bae-8727-a20655846cb3","title":"22","description":"33","file":""},{"id":"0ef39925-2440-445b-9247-3b82901cf8e6","title":"22","description":"33","file":""},{"id":"90b43990-9c05-4707-b83f-5f299e4d2f47","title":"yy","description":"yyy","file":""},{"id":"fcfb358c-4f98-4ac4-8d94-4c8492a75e28","title":"hij","description":"sds","file":"C:\\fakepath\\image 5.png"},{"id":"4ad9e5b8-10d2-48fc-8b27-9b655647a23e","title":"sadsd","description":"sadsd","file":"C:\\fakepath\\image 5.png"},{"id":"fb9db1ef-7a56-4c7c-8b26-28eada8f053a","title":"kjhkasd","description":"jnkn","file":""},{"id":"46e97ff6-6add-4d06-ab30-faf1bbd39d60","title":"adfsad","description":"adfasdfd","file":""},{"id":"969005d2-5f09-4144-bdd4-581a3f6f8242","title":"sdsd","description":"sdsd","file":""},{"id":"15a5d8b7-73b1-4df2-a3be-04253348274f","title":"cry","description":"sdsdcrcrrrry","file":""},{"id":"84866dc5-5453-4478-9879-d5a0591d0d6a","title":"cryyyy","description":"more cry","file":""},{"id":"d88c6ff5-60d3-4005-9c7d-d484a22c7d94","title":"cry so hard","description":"cry so much","file":""},{"id":"99253216-74c8-4d03-87a5-0ce8cc7f6607","title":"testing","description":"testttt","file":""}]